cfdi/__init__.py
cfdi/callbacks.py
cfdi/catalogos.py
cfdi/classes.py
cfdi/complementos.py
cfdi/constants.py
cfdi/functions.py
cfdi/models.py
cfdi/settings.py
cfdi/utils.py
cfdi/validacion_cfdi.py
cfdi/views.py
cfdi/addendas/__init__.py
cfdi/addendas/__pycache__/__init__.cpython-312.pyc
cfdi/addendas/agnico/addenda.py
cfdi/addendas/ahmsa_prueba/addenda.py
cfdi/addendas/amece/addenda.py
cfdi/addendas/asofarma/addenda.py
cfdi/addendas/coppel/addenda.py
cfdi/addendas/ford2023/addenda.py
cfdi/addendas/lacomer/addenda.py
cfdi/addendas/loreal/addenda.py
cfdi/addendas/manual/addenda.py
cfdi/addendas/manual/__pycache__/addenda.cpython-312.pyc
cfdi/addendas/multiasistencia/addenda.py
cfdi/addendas/pemex_2/addenda.py
cfdi/addendas/tiba/addenda.py
cfdi/addendas/veritiv/addenda.py
cfdi/addendas/viscofan/addenda.py
cfdi/addendas/zfsachs/addenda.py
cfdi/addendas/zobele/addenda.py
cfdi/migrations/0001_initial.py
cfdi/migrations/0002_delete_descargacfdi.py
cfdi/migrations/0003_descargacfdi.py
cfdi/migrations/0004_auto_20200429_1435.py
cfdi/migrations/0005_auto_20200430_0520.py
cfdi/migrations/0006_auto_20200430_0529.py
cfdi/migrations/0007_auto_20200527_1708.py
cfdi/migrations/0008_certificadosello.py
cfdi/migrations/0009_auto_20200730_1625.py
cfdi/migrations/0010_auto_20200730_1648.py
cfdi/migrations/0011_descargacfdi_tipo_solicitud.py
cfdi/migrations/0012_auto_20210520_1040.py
cfdi/migrations/0013_auto_20210726_2306.py
cfdi/migrations/0014_descargacfdi_archivos.py
cfdi/migrations/0015_cfdi_motivo_cancelacion_cfdi.py
cfdi/migrations/0016_cfdi_cfdis_relacionados.py
cfdi/migrations/0017_cfdi_extra.py
cfdi/migrations/0018_cfdi_tipo_relacion.py
cfdi/migrations/0019_descargacfdi_metodo_descarga.py
cfdi/migrations/0020_alter_descargacfdi_metodo_descarga.py
cfdi/migrations/0021_cfdi_cfdi_fecha_cancelacion_sat.py
cfdi/migrations/0022_alter_descargacfdi_usuario_creado.py
cfdi/migrations/0023_alter_descargacfdi_status.py
cfdi/migrations/__init__.py
cfdi/static/cfdi/codemirror/.editorconfig
django_cfdi-2.238.dist-info/METADATA
django_cfdi-2.238.dist-info/WHEEL
django_cfdi-2.238.dist-info/top_level.txt
django_cfdi-2.238.dist-info/RECORD
