Metadata-Version: 2.4
Name: django-cfdi
Version: 2.238
Summary: django-cfdi is a tool for friendly work with CFDI's .
Home-page: https://gitlab.com/admintotal/django-cfdi
Author: admintotal-dev
Requires-Dist: django>=1.8; python_version >= "3"
Requires-Dist: cfdiclient>=1.4.1; python_version >= "3"
Dynamic: author
Dynamic: description
Dynamic: description-content-type
Dynamic: home-page
Dynamic: requires-dist
Dynamic: summary
